{"nodes": [{"id": "m2_auditor_briefing", "label": "M2 Auditor Briefing", "file_type": "document", "source_file": ".agents\\sub_orch_impl\\m2_auditor\\BRIEFING.md", "source_location": null, "source_url": null, "captured_at": null, "author": null, "contributor": null}], "edges": [{"source": "m2_auditor_briefing", "target": "m2_auditor_original_request", "relation": "references", "confidence": "EXTRACTED", "confidence_score": 1.0, "source_file": ".agents\\sub_orch_impl\\m2_auditor\\BRIEFING.md", "source_location": null, "weight": 1.0}, {"source": "m2_auditor_briefing", "target": "m2_explorer_1_briefing", "relation": "conceptually_related_to", "confidence": "INFERRED", "confidence_score": 0.8, "source_file": ".agents\\sub_orch_impl\\m2_auditor\\BRIEFING.md", "source_location": null, "weight": 1.0}, {"source": "m2_auditor_briefing", "target": "m2_challenger_1_briefing", "relation": "conceptually_related_to", "confidence": "INFERRED", "confidence_score": 0.8, "source_file": ".agents\\sub_orch_impl\\m2_auditor\\BRIEFING.md", "source_location": null, "weight": 1.0}, {"source": "m2_auditor_briefing", "target": "m2_challenger_2_briefing", "relation": "conceptually_related_to", "confidence": "INFERRED", "confidence_score": 0.8, "source_file": ".agents\\sub_orch_impl\\m2_auditor\\BRIEFING.md", "source_location": null, "weight": 1.0}], "hyperedges": []}