{
  "colorGroups": [
    {
      "query": "tag:#community/Claim_Verification_Logic",
      "color": {
        "a": 1,
        "rgb": 5142951
      }
    },
    {
      "query": "tag:#community/Cache_Analysis_Utilities",
      "color": {
        "a": 1,
        "rgb": 15896107
      }
    },
    {
      "query": "tag:#community/Workspace_Resolver",
      "color": {
        "a": 1,
        "rgb": 14767961
      }
    },
    {
      "query": "tag:#community/Investigation_Briefing",
      "color": {
        "a": 1,
        "rgb": 7780274
      }
    },
    {
      "query": "tag:#community/Project_Fact_Reporting",
      "color": {
        "a": 1,
        "rgb": 5873999
      }
    },
    {
      "query": "tag:#community/Observation_Safety_Checks",
      "color": {
        "a": 1,
        "rgb": 15583560
      }
    },
    {
      "query": "tag:#community/Page_Metadata_Components",
      "color": {
        "a": 1,
        "rgb": 11565729
      }
    },
    {
      "query": "tag:#community/Vercel_Service_Integration",
      "color": {
        "a": 1,
        "rgb": 16752039
      }
    },
    {
      "query": "tag:#community/Marketing_Landing_Components",
      "color": {
        "a": 1,
        "rgb": 10253663
      }
    },
    {
      "query": "tag:#community/Recommendation_Deduplication",
      "color": {
        "a": 1,
        "rgb": 12234924
      }
    },
    {
      "query": "tag:#community/Candidate_Reconciliation",
      "color": {
        "a": 1,
        "rgb": 5142951
      }
    },
    {
      "query": "tag:#community/Project_Documentation_Context",
      "color": {
        "a": 1,
        "rgb": 15896107
      }
    },
    {
      "query": "tag:#community/AI_Application_Playbooks",
      "color": {
        "a": 1,
        "rgb": 14767961
      }
    },
    {
      "query": "tag:#community/Lead_Generation_Forms",
      "color": {
        "a": 1,
        "rgb": 7780274
      }
    },
    {
      "query": "tag:#community/Support_Topic_Matching",
      "color": {
        "a": 1,
        "rgb": 5873999
      }
    },
    {
      "query": "tag:#community/Agent_Operating_Manuals",
      "color": {
        "a": 1,
        "rgb": 15583560
      }
    },
    {
      "query": "tag:#community/Display_Label_Formatting",
      "color": {
        "a": 1,
        "rgb": 11565729
      }
    },
    {
      "query": "tag:#community/Route_Normalization",
      "color": {
        "a": 1,
        "rgb": 16752039
      }
    },
    {
      "query": "tag:#community/React_Native_Optimization",
      "color": {
        "a": 1,
        "rgb": 10253663
      }
    },
    {
      "query": "tag:#community/Interactive_UI_Components",
      "color": {
        "a": 1,
        "rgb": 12234924
      }
    },
    {
      "query": "tag:#community/OData_Query_Utilities",
      "color": {
        "a": 1,
        "rgb": 5142951
      }
    },
    {
      "query": "tag:#community/Remotion_Video_Assets",
      "color": {
        "a": 1,
        "rgb": 15896107
      }
    },
    {
      "query": "tag:#community/Lead_Database_Handler",
      "color": {
        "a": 1,
        "rgb": 14767961
      }
    },
    {
      "query": "tag:#community/App_Routing_Pages",
      "color": {
        "a": 1,
        "rgb": 7780274
      }
    },
    {
      "query": "tag:#community/SEO_and_Landing_Pages",
      "color": {
        "a": 1,
        "rgb": 5873999
      }
    },
    {
      "query": "tag:#community/TypeScript_Configuration",
      "color": {
        "a": 1,
        "rgb": 15583560
      }
    },
    {
      "query": "tag:#community/Market_Page_Components",
      "color": {
        "a": 1,
        "rgb": 11565729
      }
    },
    {
      "query": "tag:#community/Commercial_Service_Pages",
      "color": {
        "a": 1,
        "rgb": 16752039
      }
    },
    {
      "query": "tag:#community/Impact_Sanitization_Logic",
      "color": {
        "a": 1,
        "rgb": 10253663
      }
    },
    {
      "query": "tag:#community/Account_Metrics_Collection",
      "color": {
        "a": 1,
        "rgb": 12234924
      }
    },
    {
      "query": "tag:#community/Candidate_Selection_Logic",
      "color": {
        "a": 1,
        "rgb": 5142951
      }
    },
    {
      "query": "tag:#community/Sub-Agent_Output_Parser",
      "color": {
        "a": 1,
        "rgb": 15896107
      }
    },
    {
      "query": "tag:#community/Signal_Merging_Logic",
      "color": {
        "a": 1,
        "rgb": 14767961
      }
    },
    {
      "query": "tag:#community/Project_Briefing_Files",
      "color": {
        "a": 1,
        "rgb": 7780274
      }
    },
    {
      "query": "tag:#community/Project_Dependencies",
      "color": {
        "a": 1,
        "rgb": 5873999
      }
    },
    {
      "query": "tag:#community/Citation_and_Library_Mapping",
      "color": {
        "a": 1,
        "rgb": 15583560
      }
    },
    {
      "query": "tag:#community/Rate_Limiting_Logic",
      "color": {
        "a": 1,
        "rgb": 11565729
      }
    },
    {
      "query": "tag:#community/Development_Dependencies",
      "color": {
        "a": 1,
        "rgb": 16752039
      }
    },
    {
      "query": "tag:#community/Estimate_Calculator_Logic",
      "color": {
        "a": 1,
        "rgb": 10253663
      }
    },
    {
      "query": "tag:#community/Page_Header_Scanners",
      "color": {
        "a": 1,
        "rgb": 12234924
      }
    },
    {
      "query": "tag:#community/React_Architecture_Patterns",
      "color": {
        "a": 1,
        "rgb": 5142951
      }
    },
    {
      "query": "tag:#community/Middleware_Scanners",
      "color": {
        "a": 1,
        "rgb": 15896107
      }
    },
    {
      "query": "tag:#community/Budget_Summary_Generator",
      "color": {
        "a": 1,
        "rgb": 14767961
      }
    },
    {
      "query": "tag:#community/Impact_Label_Synthesis",
      "color": {
        "a": 1,
        "rgb": 7780274
      }
    },
    {
      "query": "tag:#community/Lead_Webhook_Integration",
      "color": {
        "a": 1,
        "rgb": 5873999
      }
    },
    {
      "query": "tag:#community/NPM_Script_Commands",
      "color": {
        "a": 1,
        "rgb": 15583560
      }
    },
    {
      "query": "tag:#community/Static_Site_Prerendering",
      "color": {
        "a": 1,
        "rgb": 11565729
      }
    },
    {
      "query": "tag:#community/Concurrency_Control_Utilities",
      "color": {
        "a": 1,
        "rgb": 16752039
      }
    },
    {
      "query": "tag:#community/Vercel_Hard_Gates",
      "color": {
        "a": 1,
        "rgb": 10253663
      }
    },
    {
      "query": "tag:#community/Directive_Rewriting_Utilities",
      "color": {
        "a": 1,
        "rgb": 12234924
      }
    },
    {
      "query": "tag:#community/Postgres_Indexing_Best-Practices",
      "color": {
        "a": 1,
        "rgb": 5142951
      }
    },
    {
      "query": "tag:#community/Supabase_Documentation",
      "color": {
        "a": 1,
        "rgb": 15896107
      }
    },
    {
      "query": "tag:#community/Candidate_Contract_Validation",
      "color": {
        "a": 1,
        "rgb": 14767961
      }
    },
    {
      "query": "tag:#community/Scanner_Grouping_Logic",
      "color": {
        "a": 1,
        "rgb": 7780274
      }
    },
    {
      "query": "tag:#community/Route_Extraction_Utilities",
      "color": {
        "a": 1,
        "rgb": 5873999
      }
    },
    {
      "query": "tag:#community/Graphify_Reference_Guides",
      "color": {
        "a": 1,
        "rgb": 15583560
      }
    },
    {
      "query": "tag:#community/Candidate_Display_Formatting",
      "color": {
        "a": 1,
        "rgb": 11565729
      }
    },
    {
      "query": "tag:#community/CWV_Performance_Analysis",
      "color": {
        "a": 1,
        "rgb": 16752039
      }
    },
    {
      "query": "tag:#community/Documentation_Freshness_Check",
      "color": {
        "a": 1,
        "rgb": 10253663
      }
    },
    {
      "query": "tag:#community/Frontend_Data_Models",
      "color": {
        "a": 1,
        "rgb": 12234924
      }
    },
    {
      "query": "tag:#community/Vercel_Deployment_Config",
      "color": {
        "a": 1,
        "rgb": 5142951
      }
    },
    {
      "query": "tag:#community/Documentation_Schema",
      "color": {
        "a": 1,
        "rgb": 15896107
      }
    },
    {
      "query": "tag:#community/Provider_Rate_Limiting",
      "color": {
        "a": 1,
        "rgb": 14767961
      }
    },
    {
      "query": "tag:#community/Framework_Support_Classification",
      "color": {
        "a": 1,
        "rgb": 7780274
      }
    },
    {
      "query": "tag:#community/Package_Metadata",
      "color": {
        "a": 1,
        "rgb": 5873999
      }
    },
    {
      "query": "tag:#community/Suspense_Deduplication_Scanner",
      "color": {
        "a": 1,
        "rgb": 15583560
      }
    },
    {
      "query": "tag:#community/Edge_Runtime_Scanner",
      "color": {
        "a": 1,
        "rgb": 11565729
      }
    },
    {
      "query": "tag:#community/Static_Asset_Scanner",
      "color": {
        "a": 1,
        "rgb": 16752039
      }
    },
    {
      "query": "tag:#community/Build_Cache_Scanner",
      "color": {
        "a": 1,
        "rgb": 10253663
      }
    },
    {
      "query": "tag:#community/Cache_Date_Scanner",
      "color": {
        "a": 1,
        "rgb": 12234924
      }
    },
    {
      "query": "tag:#community/Documentation_Build_Script",
      "color": {
        "a": 1,
        "rgb": 5142951
      }
    },
    {
      "query": "tag:#community/View_Transition_Patterns",
      "color": {
        "a": 1,
        "rgb": 15896107
      }
    },
    {
      "query": "tag:#community/Codex_Deployment_Script",
      "color": {
        "a": 1,
        "rgb": 14767961
      }
    },
    {
      "query": "tag:#community/Framework_Deployment_Script",
      "color": {
        "a": 1,
        "rgb": 7780274
      }
    },
    {
      "query": "tag:#community/Design_System_Guidelines",
      "color": {
        "a": 1,
        "rgb": 5873999
      }
    },
    {
      "query": "tag:#community/Report_Formatting_Utilities",
      "color": {
        "a": 1,
        "rgb": 15583560
      }
    },
    {
      "query": "tag:#community/Cost_Coverage_Analysis",
      "color": {
        "a": 1,
        "rgb": 11565729
      }
    },
    {
      "query": "tag:#community/Metric_Query_Normalization",
      "color": {
        "a": 1,
        "rgb": 16752039
      }
    },
    {
      "query": "tag:#community/Undeclared_Dependency_Scanner",
      "color": {
        "a": 1,
        "rgb": 10253663
      }
    },
    {
      "query": "tag:#community/Image_Optimization_Scanner",
      "color": {
        "a": 1,
        "rgb": 12234924
      }
    },
    {
      "query": "tag:#community/Brand_Asset_Generator",
      "color": {
        "a": 1,
        "rgb": 5142951
      }
    },
    {
      "query": "tag:#community/Accessibility_Testing",
      "color": {
        "a": 1,
        "rgb": 15896107
      }
    },
    {
      "query": "tag:#community/External_API_Scanner",
      "color": {
        "a": 1,
        "rgb": 14767961
      }
    },
    {
      "query": "tag:#community/Cold_Start_Analysis",
      "color": {
        "a": 1,
        "rgb": 7780274
      }
    },
    {
      "query": "tag:#community/Bot_Protection_Analysis",
      "color": {
        "a": 1,
        "rgb": 5873999
      }
    },
    {
      "query": "tag:#community/Fluid_Compute_Analysis",
      "color": {
        "a": 1,
        "rgb": 15583560
      }
    },
    {
      "query": "tag:#community/Route_Error_Analysis",
      "color": {
        "a": 1,
        "rgb": 11565729
      }
    },
    {
      "query": "tag:#community/Slow_Route_Analysis",
      "color": {
        "a": 1,
        "rgb": 16752039
      }
    },
    {
      "query": "tag:#community/Core_Type_Definitions",
      "color": {
        "a": 1,
        "rgb": 10253663
      }
    },
    {
      "query": "tag:#community/Cache_Hit_Analysis",
      "color": {
        "a": 1,
        "rgb": 12234924
      }
    },
    {
      "query": "tag:#community/Usage_Spike_Triage",
      "color": {
        "a": 1,
        "rgb": 5142951
      }
    },
    {
      "query": "tag:#community/Pre-release_Feature_Flags",
      "color": {
        "a": 1,
        "rgb": 15896107
      }
    },
    {
      "query": "tag:#community/Sitemap_Generation",
      "color": {
        "a": 1,
        "rgb": 14767961
      }
    },
    {
      "query": "tag:#community/Painting_Service_Components",
      "color": {
        "a": 1,
        "rgb": 7780274
      }
    },
    {
      "query": "tag:#community/Repository_Standards",
      "color": {
        "a": 1,
        "rgb": 5873999
      }
    },
    {
      "query": "tag:#community/CI/CD_Workflows",
      "color": {
        "a": 1,
        "rgb": 15583560
      }
    },
    {
      "query": "tag:#community/Database_Connection_Management",
      "color": {
        "a": 1,
        "rgb": 11565729
      }
    },
    {
      "query": "tag:#community/SQL_Query_Optimization",
      "color": {
        "a": 1,
        "rgb": 16752039
      }
    },
    {
      "query": "tag:#community/Build_Minutes_Analysis",
      "color": {
        "a": 1,
        "rgb": 10253663
      }
    },
    {
      "query": "tag:#community/Function_Duration_Analysis",
      "color": {
        "a": 1,
        "rgb": 12234924
      }
    },
    {
      "query": "tag:#community/Community_100",
      "color": {
        "a": 1,
        "rgb": 5142951
      }
    },
    {
      "query": "tag:#community/Community_101",
      "color": {
        "a": 1,
        "rgb": 15896107
      }
    },
    {
      "query": "tag:#community/Community_102",
      "color": {
        "a": 1,
        "rgb": 14767961
      }
    },
    {
      "query": "tag:#community/Community_103",
      "color": {
        "a": 1,
        "rgb": 7780274
      }
    },
    {
      "query": "tag:#community/Community_104",
      "color": {
        "a": 1,
        "rgb": 5873999
      }
    },
    {
      "query": "tag:#community/Community_105",
      "color": {
        "a": 1,
        "rgb": 15583560
      }
    },
    {
      "query": "tag:#community/Community_106",
      "color": {
        "a": 1,
        "rgb": 11565729
      }
    },
    {
      "query": "tag:#community/Community_109",
      "color": {
        "a": 1,
        "rgb": 12234924
      }
    },
    {
      "query": "tag:#community/Community_110",
      "color": {
        "a": 1,
        "rgb": 5142951
      }
    },
    {
      "query": "tag:#community/Community_111",
      "color": {
        "a": 1,
        "rgb": 15896107
      }
    },
    {
      "query": "tag:#community/Community_112",
      "color": {
        "a": 1,
        "rgb": 14767961
      }
    },
    {
      "query": "tag:#community/Community_113",
      "color": {
        "a": 1,
        "rgb": 7780274
      }
    },
    {
      "query": "tag:#community/Community_114",
      "color": {
        "a": 1,
        "rgb": 5873999
      }
    },
    {
      "query": "tag:#community/Community_115",
      "color": {
        "a": 1,
        "rgb": 15583560
      }
    },
    {
      "query": "tag:#community/Community_116",
      "color": {
        "a": 1,
        "rgb": 11565729
      }
    },
    {
      "query": "tag:#community/Community_117",
      "color": {
        "a": 1,
        "rgb": 16752039
      }
    },
    {
      "query": "tag:#community/Community_118",
      "color": {
        "a": 1,
        "rgb": 10253663
      }
    },
    {
      "query": "tag:#community/Community_119",
      "color": {
        "a": 1,
        "rgb": 12234924
      }
    },
    {
      "query": "tag:#community/Community_120",
      "color": {
        "a": 1,
        "rgb": 5142951
      }
    },
    {
      "query": "tag:#community/Community_121",
      "color": {
        "a": 1,
        "rgb": 15896107
      }
    },
    {
      "query": "tag:#community/Community_122",
      "color": {
        "a": 1,
        "rgb": 14767961
      }
    },
    {
      "query": "tag:#community/Community_123",
      "color": {
        "a": 1,
        "rgb": 7780274
      }
    },
    {
      "query": "tag:#community/Community_124",
      "color": {
        "a": 1,
        "rgb": 5873999
      }
    },
    {
      "query": "tag:#community/Community_125",
      "color": {
        "a": 1,
        "rgb": 15583560
      }
    },
    {
      "query": "tag:#community/Community_126",
      "color": {
        "a": 1,
        "rgb": 11565729
      }
    },
    {
      "query": "tag:#community/Community_127",
      "color": {
        "a": 1,
        "rgb": 16752039
      }
    },
    {
      "query": "tag:#community/Community_128",
      "color": {
        "a": 1,
        "rgb": 10253663
      }
    },
    {
      "query": "tag:#community/Community_129",
      "color": {
        "a": 1,
        "rgb": 12234924
      }
    },
    {
      "query": "tag:#community/Community_130",
      "color": {
        "a": 1,
        "rgb": 5142951
      }
    },
    {
      "query": "tag:#community/Community_131",
      "color": {
        "a": 1,
        "rgb": 15896107
      }
    },
    {
      "query": "tag:#community/Community_132",
      "color": {
        "a": 1,
        "rgb": 14767961
      }
    },
    {
      "query": "tag:#community/Community_133",
      "color": {
        "a": 1,
        "rgb": 7780274
      }
    },
    {
      "query": "tag:#community/Community_134",
      "color": {
        "a": 1,
        "rgb": 5873999
      }
    },
    {
      "query": "tag:#community/Community_135",
      "color": {
        "a": 1,
        "rgb": 15583560
      }
    },
    {
      "query": "tag:#community/Community_136",
      "color": {
        "a": 1,
        "rgb": 11565729
      }
    },
    {
      "query": "tag:#community/Community_137",
      "color": {
        "a": 1,
        "rgb": 16752039
      }
    },
    {
      "query": "tag:#community/Community_138",
      "color": {
        "a": 1,
        "rgb": 10253663
      }
    },
    {
      "query": "tag:#community/Community_139",
      "color": {
        "a": 1,
        "rgb": 12234924
      }
    },
    {
      "query": "tag:#community/Community_140",
      "color": {
        "a": 1,
        "rgb": 5142951
      }
    },
    {
      "query": "tag:#community/Community_141",
      "color": {
        "a": 1,
        "rgb": 15896107
      }
    },
    {
      "query": "tag:#community/Community_142",
      "color": {
        "a": 1,
        "rgb": 14767961
      }
    },
    {
      "query": "tag:#community/Community_143",
      "color": {
        "a": 1,
        "rgb": 7780274
      }
    },
    {
      "query": "tag:#community/Community_144",
      "color": {
        "a": 1,
        "rgb": 5873999
      }
    },
    {
      "query": "tag:#community/Community_145",
      "color": {
        "a": 1,
        "rgb": 15583560
      }
    },
    {
      "query": "tag:#community/Community_146",
      "color": {
        "a": 1,
        "rgb": 11565729
      }
    },
    {
      "query": "tag:#community/Community_147",
      "color": {
        "a": 1,
        "rgb": 16752039
      }
    },
    {
      "query": "tag:#community/Community_148",
      "color": {
        "a": 1,
        "rgb": 10253663
      }
    },
    {
      "query": "tag:#community/Community_149",
      "color": {
        "a": 1,
        "rgb": 12234924
      }
    },
    {
      "query": "tag:#community/Community_150",
      "color": {
        "a": 1,
        "rgb": 5142951
      }
    },
    {
      "query": "tag:#community/Community_151",
      "color": {
        "a": 1,
        "rgb": 15896107
      }
    },
    {
      "query": "tag:#community/Community_152",
      "color": {
        "a": 1,
        "rgb": 14767961
      }
    },
    {
      "query": "tag:#community/Community_153",
      "color": {
        "a": 1,
        "rgb": 7780274
      }
    },
    {
      "query": "tag:#community/Community_154",
      "color": {
        "a": 1,
        "rgb": 5873999
      }
    },
    {
      "query": "tag:#community/Community_155",
      "color": {
        "a": 1,
        "rgb": 15583560
      }
    },
    {
      "query": "tag:#community/Community_156",
      "color": {
        "a": 1,
        "rgb": 11565729
      }
    },
    {
      "query": "tag:#community/Community_157",
      "color": {
        "a": 1,
        "rgb": 16752039
      }
    },
    {
      "query": "tag:#community/Community_158",
      "color": {
        "a": 1,
        "rgb": 10253663
      }
    },
    {
      "query": "tag:#community/Community_159",
      "color": {
        "a": 1,
        "rgb": 12234924
      }
    },
    {
      "query": "tag:#community/Community_160",
      "color": {
        "a": 1,
        "rgb": 5142951
      }
    },
    {
      "query": "tag:#community/Community_161",
      "color": {
        "a": 1,
        "rgb": 15896107
      }
    },
    {
      "query": "tag:#community/Community_162",
      "color": {
        "a": 1,
        "rgb": 14767961
      }
    },
    {
      "query": "tag:#community/Community_163",
      "color": {
        "a": 1,
        "rgb": 7780274
      }
    },
    {
      "query": "tag:#community/Community_164",
      "color": {
        "a": 1,
        "rgb": 5873999
      }
    },
    {
      "query": "tag:#community/Community_165",
      "color": {
        "a": 1,
        "rgb": 15583560
      }
    },
    {
      "query": "tag:#community/Community_166",
      "color": {
        "a": 1,
        "rgb": 11565729
      }
    },
    {
      "query": "tag:#community/Community_167",
      "color": {
        "a": 1,
        "rgb": 16752039
      }
    },
    {
      "query": "tag:#community/Community_168",
      "color": {
        "a": 1,
        "rgb": 10253663
      }
    },
    {
      "query": "tag:#community/Community_169",
      "color": {
        "a": 1,
        "rgb": 12234924
      }
    },
    {
      "query": "tag:#community/Community_170",
      "color": {
        "a": 1,
        "rgb": 5142951
      }
    },
    {
      "query": "tag:#community/Community_171",
      "color": {
        "a": 1,
        "rgb": 15896107
      }
    },
    {
      "query": "tag:#community/Community_172",
      "color": {
        "a": 1,
        "rgb": 14767961
      }
    },
    {
      "query": "tag:#community/Community_173",
      "color": {
        "a": 1,
        "rgb": 7780274
      }
    },
    {
      "query": "tag:#community/Community_174",
      "color": {
        "a": 1,
        "rgb": 5873999
      }
    },
    {
      "query": "tag:#community/Community_175",
      "color": {
        "a": 1,
        "rgb": 15583560
      }
    },
    {
      "query": "tag:#community/Community_176",
      "color": {
        "a": 1,
        "rgb": 11565729
      }
    },
    {
      "query": "tag:#community/Community_177",
      "color": {
        "a": 1,
        "rgb": 16752039
      }
    },
    {
      "query": "tag:#community/Community_178",
      "color": {
        "a": 1,
        "rgb": 10253663
      }
    },
    {
      "query": "tag:#community/Community_179",
      "color": {
        "a": 1,
        "rgb": 12234924
      }
    },
    {
      "query": "tag:#community/Community_180",
      "color": {
        "a": 1,
        "rgb": 5142951
      }
    },
    {
      "query": "tag:#community/Community_181",
      "color": {
        "a": 1,
        "rgb": 15896107
      }
    },
    {
      "query": "tag:#community/Community_182",
      "color": {
        "a": 1,
        "rgb": 14767961
      }
    },
    {
      "query": "tag:#community/Community_183",
      "color": {
        "a": 1,
        "rgb": 7780274
      }
    },
    {
      "query": "tag:#community/Community_184",
      "color": {
        "a": 1,
        "rgb": 5873999
      }
    },
    {
      "query": "tag:#community/Community_185",
      "color": {
        "a": 1,
        "rgb": 15583560
      }
    },
    {
      "query": "tag:#community/Community_186",
      "color": {
        "a": 1,
        "rgb": 11565729
      }
    },
    {
      "query": "tag:#community/Community_187",
      "color": {
        "a": 1,
        "rgb": 16752039
      }
    },
    {
      "query": "tag:#community/Community_188",
      "color": {
        "a": 1,
        "rgb": 10253663
      }
    },
    {
      "query": "tag:#community/Community_189",
      "color": {
        "a": 1,
        "rgb": 12234924
      }
    },
    {
      "query": "tag:#community/Community_190",
      "color": {
        "a": 1,
        "rgb": 5142951
      }
    },
    {
      "query": "tag:#community/Community_191",
      "color": {
        "a": 1,
        "rgb": 15896107
      }
    },
    {
      "query": "tag:#community/Community_192",
      "color": {
        "a": 1,
        "rgb": 14767961
      }
    },
    {
      "query": "tag:#community/Community_193",
      "color": {
        "a": 1,
        "rgb": 7780274
      }
    },
    {
      "query": "tag:#community/Community_194",
      "color": {
        "a": 1,
        "rgb": 5873999
      }
    },
    {
      "query": "tag:#community/Community_195",
      "color": {
        "a": 1,
        "rgb": 15583560
      }
    },
    {
      "query": "tag:#community/Community_196",
      "color": {
        "a": 1,
        "rgb": 11565729
      }
    },
    {
      "query": "tag:#community/Community_197",
      "color": {
        "a": 1,
        "rgb": 16752039
      }
    },
    {
      "query": "tag:#community/Community_198",
      "color": {
        "a": 1,
        "rgb": 10253663
      }
    },
    {
      "query": "tag:#community/Community_199",
      "color": {
        "a": 1,
        "rgb": 12234924
      }
    },
    {
      "query": "tag:#community/Community_200",
      "color": {
        "a": 1,
        "rgb": 5142951
      }
    },
    {
      "query": "tag:#community/Community_201",
      "color": {
        "a": 1,
        "rgb": 15896107
      }
    },
    {
      "query": "tag:#community/Community_202",
      "color": {
        "a": 1,
        "rgb": 14767961
      }
    },
    {
      "query": "tag:#community/Community_203",
      "color": {
        "a": 1,
        "rgb": 7780274
      }
    },
    {
      "query": "tag:#community/Community_204",
      "color": {
        "a": 1,
        "rgb": 5873999
      }
    },
    {
      "query": "tag:#community/Community_205",
      "color": {
        "a": 1,
        "rgb": 15583560
      }
    },
    {
      "query": "tag:#community/Community_206",
      "color": {
        "a": 1,
        "rgb": 11565729
      }
    },
    {
      "query": "tag:#community/Community_207",
      "color": {
        "a": 1,
        "rgb": 16752039
      }
    },
    {
      "query": "tag:#community/Community_208",
      "color": {
        "a": 1,
        "rgb": 10253663
      }
    },
    {
      "query": "tag:#community/Community_209",
      "color": {
        "a": 1,
        "rgb": 12234924
      }
    },
    {
      "query": "tag:#community/Community_210",
      "color": {
        "a": 1,
        "rgb": 5142951
      }
    },
    {
      "query": "tag:#community/Community_211",
      "color": {
        "a": 1,
        "rgb": 15896107
      }
    },
    {
      "query": "tag:#community/Community_212",
      "color": {
        "a": 1,
        "rgb": 14767961
      }
    },
    {
      "query": "tag:#community/Community_213",
      "color": {
        "a": 1,
        "rgb": 7780274
      }
    },
    {
      "query": "tag:#community/Community_214",
      "color": {
        "a": 1,
        "rgb": 5873999
      }
    },
    {
      "query": "tag:#community/Community_215",
      "color": {
        "a": 1,
        "rgb": 15583560
      }
    },
    {
      "query": "tag:#community/Community_216",
      "color": {
        "a": 1,
        "rgb": 11565729
      }
    },
    {
      "query": "tag:#community/Community_217",
      "color": {
        "a": 1,
        "rgb": 16752039
      }
    },
    {
      "query": "tag:#community/Community_218",
      "color": {
        "a": 1,
        "rgb": 10253663
      }
    },
    {
      "query": "tag:#community/Community_219",
      "color": {
        "a": 1,
        "rgb": 12234924
      }
    },
    {
      "query": "tag:#community/Community_220",
      "color": {
        "a": 1,
        "rgb": 5142951
      }
    },
    {
      "query": "tag:#community/Community_221",
      "color": {
        "a": 1,
        "rgb": 15896107
      }
    },
    {
      "query": "tag:#community/Community_222",
      "color": {
        "a": 1,
        "rgb": 14767961
      }
    },
    {
      "query": "tag:#community/Community_223",
      "color": {
        "a": 1,
        "rgb": 7780274
      }
    },
    {
      "query": "tag:#community/Community_224",
      "color": {
        "a": 1,
        "rgb": 5873999
      }
    },
    {
      "query": "tag:#community/Community_225",
      "color": {
        "a": 1,
        "rgb": 15583560
      }
    },
    {
      "query": "tag:#community/Community_226",
      "color": {
        "a": 1,
        "rgb": 11565729
      }
    },
    {
      "query": "tag:#community/Community_227",
      "color": {
        "a": 1,
        "rgb": 16752039
      }
    },
    {
      "query": "tag:#community/Community_228",
      "color": {
        "a": 1,
        "rgb": 10253663
      }
    },
    {
      "query": "tag:#community/Community_229",
      "color": {
        "a": 1,
        "rgb": 12234924
      }
    },
    {
      "query": "tag:#community/Community_230",
      "color": {
        "a": 1,
        "rgb": 5142951
      }
    },
    {
      "query": "tag:#community/Community_231",
      "color": {
        "a": 1,
        "rgb": 15896107
      }
    },
    {
      "query": "tag:#community/Community_232",
      "color": {
        "a": 1,
        "rgb": 14767961
      }
    }
  ]
}